hnswlib_noderag.cp310-win_amd64.pyd
hnswlib_noderag-0.8.2.dist-info/LICENSE
hnswlib_noderag-0.8.2.dist-info/METADATA
hnswlib_noderag-0.8.2.dist-info/WHEEL
hnswlib_noderag-0.8.2.dist-info/top_level.txt
hnswlib_noderag-0.8.2.dist-info/RECORD
