Metadata-Version: 2.2
Name: hnswlib_noderag
Version: 0.8.2
Summary: hnswlib adapted for Node RAG project
Home-page: https://github.com/yurymalkov/hnsw
Author: Yury Malkov and others(original author),Tianyang Xu and others(NodeRAG team)
Classifier: Development Status :: 5 - Production/Stable
Classifier: Intended Audience :: Science/Research
Classifier: License :: OSI Approved :: Apache Software License
Classifier: Programming Language :: Python :: 3
Classifier: Programming Language :: Python :: 3.10
Classifier: Programming Language :: Python :: 3.11
Requires-Python: >=3.10,<4.0
License-File: LICENSE
Requires-Dist: numpy
Dynamic: author
Dynamic: classifier
Dynamic: home-page
Dynamic: requires-dist
Dynamic: requires-python
Dynamic: summary
